hack/__init__.py
hack/courses.py
hack/utils.py
Spectro1-0.1.0.dist-info/METADATA
Spectro1-0.1.0.dist-info/WHEEL
Spectro1-0.1.0.dist-info/top_level.txt
Spectro1-0.1.0.dist-info/RECORD
