Metadata-Version: 2.1
Name: Spectro1
Version: 0.1.0
Summary: Una biblioteca para consultar los cursos del tito savitar
Home-page: https://Spectro1.io
Author: Spectro1
